{
  "grandTotal": 241702,
  "grandTotalNew": 203349,
  "grandTotalNewConversionRate": 1781,
  "grandTotalUpdates": 38353,
  "grandTotalCountrySplit": {
    "USA": 230844,
    "CAN": 4545,
    "GBR": 3611,
    "FRA": 855,
    "ESP": 816,
    "DEU": 729,
    "IRL": 271,
    "COL": 5,
    "BRA": 2,
    "ECU": 2,
    "MEX": 2,
    "SAU": 2,
    "BGD": 1,
    "IMN": 1,
    "ISR": 1,
    "PRI": 1,
    "OMN": 1,
    "UZB": 1,
    "SWE": 1,
    "CZE": 1,
    "TUR": 1,
    "VNM": 1,
    "AUS": 1,
    "GRC": 1,
    "POL": 1,
    "ARG": 1,
    "CHN": 1,
    "ARE": 1,
    "CYM": 1,
    "NPL": 1
  },
  "dailyTotal": 274,
  "dailyTotalNew": 187,
  "dailyTotalUpdates": 87,
  "dailyTotalCountrySplit": {
    "USA": 247,
    "GBR": 13,
    "CAN": 8,
    "FRA": 3,
    "DEU": 2,
    "ESP": 1
  },
  "dailyTotalNewCountrySplit": {
    "USA": 164,
    "GBR": 11,
    "CAN": 6,
    "FRA": 3,
    "DEU": 2,
    "ESP": 1
  },
  "dailyTotalUpdatesCountrySplit": {
    "USA": 83,
    "CAN": 2,
    "GBR": 2
  },
  "grandTotalDeuNewOptInConfirmed": 192,
  "dailyTotalDeuNewOptInConfirmed": 0,
  "grandTotalRetention": 132904,
  "grandTotalCountrySplitRetention": {
    "USA": 123089,
    "CAN": 4333,
    "GBR": 3400,
    "FRA": 824,
    "ESP": 787,
    "IRL": 254,
    "DEU": 199,
    "COL": 4,
    "BRA": 2,
    "BGD": 1,
    "ISR": 1,
    "PRI": 1,
    "OMN": 1,
    "UZB": 1,
    "TUR": 1,
    "ARG": 1,
    "CHN": 1,
    "MEX": 1,
    "ARE": 1,
    "SAU": 1,
    "NPL": 1
  },
  "lastUpdated": "2026-07-19_03-11"
}