{
  "grandTotal": 35963,
  "grandTotalNew": 28598,
  "grandTotalNewConversionRate": 565,
  "grandTotalUpdates": 7365,
  "grandTotalCountrySplit": {
    "USA": 32112,
    "GBR": 1532,
    "CAN": 1405,
    "FRA": 300,
    "DEU": 280,
    "ESP": 228,
    "IRL": 98,
    "COL": 1,
    "OMN": 1,
    "BRA": 1,
    "CHN": 1,
    "MEX": 1,
    "ARE": 1,
    "CYM": 1,
    "SAU": 1
  },
  "dailyTotal": 1512,
  "dailyTotalNew": 1444,
  "dailyTotalUpdates": 68,
  "dailyTotalCountrySplit": {
    "USA": 1460,
    "GBR": 20,
    "CAN": 11,
    "DEU": 10,
    "ESP": 8,
    "FRA": 3
  },
  "dailyTotalNewCountrySplit": {
    "USA": 1408,
    "GBR": 13,
    "DEU": 8,
    "CAN": 7,
    "ESP": 5,
    "FRA": 3
  },
  "dailyTotalUpdatesCountrySplit": {
    "USA": 52,
    "GBR": 7,
    "CAN": 4,
    "ESP": 3,
    "DEU": 2
  },
  "grandTotalDeuNewOptInConfirmed": 83,
  "dailyTotalDeuNewOptInConfirmed": 0,
  "lastUpdated": "2026-06-25_06-38"
}