{
  "grandTotal": 37751,
  "grandTotalNew": 29892,
  "grandTotalNewConversionRate": 614,
  "grandTotalUpdates": 7859,
  "grandTotalCountrySplit": {
    "USA": 33679,
    "GBR": 1591,
    "CAN": 1512,
    "FRA": 318,
    "DEU": 293,
    "ESP": 246,
    "IRL": 103,
    "COL": 1,
    "OMN": 1,
    "BRA": 1,
    "ECU": 1,
    "CHN": 1,
    "MEX": 1,
    "ARE": 1,
    "CYM": 1,
    "SAU": 1
  },
  "dailyTotal": 164,
  "dailyTotalNew": 114,
  "dailyTotalUpdates": 50,
  "dailyTotalCountrySplit": {
    "USA": 118,
    "GBR": 22,
    "CAN": 10,
    "ESP": 6,
    "FRA": 4,
    "DEU": 3,
    "IRL": 1
  },
  "dailyTotalNewCountrySplit": {
    "USA": 82,
    "GBR": 15,
    "CAN": 7,
    "ESP": 5,
    "FRA": 3,
    "IRL": 1,
    "DEU": 1
  },
  "dailyTotalUpdatesCountrySplit": {
    "USA": 36,
    "GBR": 7,
    "CAN": 3,
    "DEU": 2,
    "FRA": 1,
    "ESP": 1
  },
  "grandTotalDeuNewOptInConfirmed": 90,
  "dailyTotalDeuNewOptInConfirmed": 0,
  "lastUpdated": "2026-06-26_05-48"
}