{
  "grandTotal": 28805,
  "grandTotalNew": 22285,
  "grandTotalUpdates": 6520,
  "grandTotalCountrySplit": {
    "USA": 25302,
    "GBR": 1421,
    "CAN": 1256,
    "FRA": 266,
    "DEU": 258,
    "ESP": 204,
    "IRL": 91,
    "COL": 1,
    "OMN": 1,
    "BRA": 1,
    "MEX": 1,
    "ARE": 1,
    "CYM": 1,
    "SAU": 1
  },
  "dailyTotal": 470,
  "dailyTotalNew": 307,
  "dailyTotalUpdates": 163,
  "dailyTotalCountrySplit": {
    "USA": 348,
    "CAN": 42,
    "GBR": 36,
    "DEU": 22,
    "ESP": 11,
    "FRA": 9,
    "IRL": 2
  },
  "dailyTotalNewCountrySplit": {
    "USA": 232,
    "GBR": 24,
    "CAN": 22,
    "DEU": 11,
    "FRA": 9,
    "ESP": 8,
    "IRL": 1
  },
  "dailyTotalUpdatesCountrySplit": {
    "USA": 116,
    "CAN": 20,
    "GBR": 12,
    "DEU": 11,
    "ESP": 3,
    "IRL": 1
  },
  "grandTotalDeuNewOptInConfirmed": 73,
  "dailyTotalDeuNewOptInConfirmed": 0,
  "lastUpdated": "2026-06-23_09-46"
}